ihypy/__init__.py
ihypy/instrument.py
ihypy/system.py
ihypy/test.py
ihypy/theory.py
ihypy-0.0.5.dist-info/LICENSE.txt
ihypy-0.0.5.dist-info/METADATA
ihypy-0.0.5.dist-info/WHEEL
ihypy-0.0.5.dist-info/top_level.txt
ihypy-0.0.5.dist-info/RECORD
