Metadata-Version: 2.1
Name: ihypy
Version: 0.0.5
Summary: WIP Python musical analysis module
License: MIT
Keywords: music,python
Platform: UNKNOWN
Classifier: Programming Language :: Python :: 3
License-File: LICENSE.txt
Requires-Dist: simpleaudio
Requires-Dist: pydub
